{"Title":"Tao wang","Year":"1975","Released":"25 Oct 1975","Runtime":"84 min","Genre":"Action","Director":"Cheh Chang, Chung Sun","Writer":"Kuang Ni","Actors":"Shen Chan, Kuan Tai Chen, Wo-fu Chen","Plot":"Gu Hui, a member of the \u0027Wolf Head Gang\u0027 becomes unhappy after their new chief decides to abandon their old code of conduct.","Language":"Mandarin","Country":"Hong Kong","Poster":"https://m.media-amazon.com/images/M/MV5BZWYxYzUyNTUtZjBiMy00MDU4LTliMjUtMGY2NDJiNzA3ZDE4XkEyXkFqcGdeQXVyMjUyNDk2ODc@._V1_SX300.jpg","Ratings":[{"Source":"Internet Movie Database","Value":"6.3/10"}],"imdbRating":"6.3","imdbVotes":"60","imdbID":"tt0072713","Type":"movie","Response":"True"}